WuaiPojieLuntanjinghuaJi2018DiwuBufen/README.md
WuaiPojieLuntanjinghuaJi2018DiwuBufen/__init__.py
WuaiPojieLuntanjinghuaJi2018DiwuBufen/__main__.py
WuaiPojieLuntanjinghuaJi2018DiwuBufen/file.epub
WuaiPojieLuntanjinghuaJi2018DiwuBufen/index.html
WuaiPojieLuntanjinghuaJi2018DiwuBufen/css/__init__.py
WuaiPojieLuntanjinghuaJi2018DiwuBufen/css/annotations.css
WuaiPojieLuntanjinghuaJi2018DiwuBufen/css/main.css
WuaiPojieLuntanjinghuaJi2018DiwuBufen/css/normalize.css
WuaiPojieLuntanjinghuaJi2018DiwuBufen/css/popup.css
WuaiPojieLuntanjinghuaJi2018DiwuBufen/font/__init__.py
WuaiPojieLuntanjinghuaJi2018DiwuBufen/font/fontello.eot
WuaiPojieLuntanjinghuaJi2018DiwuBufen/font/fontello.svg
WuaiPojieLuntanjinghuaJi2018DiwuBufen/font/fontello.ttf
WuaiPojieLuntanjinghuaJi2018DiwuBufen/font/fontello.woff
WuaiPojieLuntanjinghuaJi2018DiwuBufen/img/__init__.py
WuaiPojieLuntanjinghuaJi2018DiwuBufen/img/annotator-glyph-sprite.png
WuaiPojieLuntanjinghuaJi2018DiwuBufen/img/annotator-icon-sprite.png
WuaiPojieLuntanjinghuaJi2018DiwuBufen/img/apple-touch-icon.png
WuaiPojieLuntanjinghuaJi2018DiwuBufen/img/cancelfullscreen.png
WuaiPojieLuntanjinghuaJi2018DiwuBufen/img/close.png
WuaiPojieLuntanjinghuaJi2018DiwuBufen/img/fullscreen.png
WuaiPojieLuntanjinghuaJi2018DiwuBufen/img/loader.gif
WuaiPojieLuntanjinghuaJi2018DiwuBufen/img/menu-icon.png
WuaiPojieLuntanjinghuaJi2018DiwuBufen/img/save.png
WuaiPojieLuntanjinghuaJi2018DiwuBufen/img/saved.png
WuaiPojieLuntanjinghuaJi2018DiwuBufen/img/settings-s.png
WuaiPojieLuntanjinghuaJi2018DiwuBufen/img/settings.png
WuaiPojieLuntanjinghuaJi2018DiwuBufen/img/star.png
WuaiPojieLuntanjinghuaJi2018DiwuBufen/js/__init__.py
WuaiPojieLuntanjinghuaJi2018DiwuBufen/js/epub.js
WuaiPojieLuntanjinghuaJi2018DiwuBufen/js/epub.min.js
WuaiPojieLuntanjinghuaJi2018DiwuBufen/js/epub.min.map
WuaiPojieLuntanjinghuaJi2018DiwuBufen/js/hooks.min.js
WuaiPojieLuntanjinghuaJi2018DiwuBufen/js/hooks.min.map
WuaiPojieLuntanjinghuaJi2018DiwuBufen/js/reader.js
wuai_pojie_luntanjinghua_ji_2018_diwu_bufen-2024.3.5.0.dist-info/METADATA
wuai_pojie_luntanjinghua_ji_2018_diwu_bufen-2024.3.5.0.dist-info/WHEEL
wuai_pojie_luntanjinghua_ji_2018_diwu_bufen-2024.3.5.0.dist-info/entry_points.txt
wuai_pojie_luntanjinghua_ji_2018_diwu_bufen-2024.3.5.0.dist-info/top_level.txt
wuai_pojie_luntanjinghua_ji_2018_diwu_bufen-2024.3.5.0.dist-info/RECORD
